init_service/__init__.py
init_service/init_service.py
init_service/pyratemp.py
init_service/templates/library/.gitignore
init_service/templates/library/build.sbt
init_service/templates/library/project/LibDependencies.scala
init_service/templates/library/project/build.properties
init_service/templates/library/project/plugins.sbt
init_service/templates/library/src/main/scala/uk/gov/hmrc/hello/HelloWorld.scala
init_service/templates/library/src/test/scala/uk/gov/hmrc/hello/HelloWorldSpec.scala
init_service/templates/service/.gitignore
init_service/templates/service/app/assets/stylesheets/application.scss
init_service/templates/service/app/config/AppConfig.scala
init_service/templates/service/app/config/ErrorHandler.scala
init_service/templates/service/app/config/Module.scala
init_service/templates/service/app/controllers/DocumentationController.scala
init_service/templates/service/app/controllers/HelloWorldController.scala
init_service/templates/service/app/controllers/MicroserviceHelloWorldController.scala
init_service/templates/service/app/views/ErrorTemplate.scala.html
init_service/templates/service/app/views/HelloWorldPage.scala.html
init_service/templates/service/app/views/Layout.scala.html
init_service/templates/service/build.sbt
init_service/templates/service/conf/app.routes
init_service/templates/service/conf/application-json-logger.xml
init_service/templates/service/conf/application.conf
init_service/templates/service/conf/definition.routes
init_service/templates/service/conf/logback.xml
init_service/templates/service/conf/messages
init_service/templates/service/conf/messages.cy
init_service/templates/service/conf/prod.routes
init_service/templates/service/conf/testOnlyDoNotUseInAppConf.routes
init_service/templates/service/it/HealthEndpointIntegrationSpec.scala
init_service/templates/service/project/AppDependencies.scala
init_service/templates/service/project/CodeCoverageSettings.scala
init_service/templates/service/project/build.properties
init_service-0.8.0.dist-info/LICENSE
init_service-0.8.0.dist-info/METADATA
init_service-0.8.0.dist-info/WHEEL
init_service-0.8.0.dist-info/entry_points.txt
init_service-0.8.0.dist-info/RECORD
